feastdays/__init__.py
feastdays/core.py
feastdays/data/feast_days.json
feastdays-1.1.0.dist-info/licenses/LICENSE
feastdays-1.1.0.dist-info/METADATA
feastdays-1.1.0.dist-info/WHEEL
feastdays-1.1.0.dist-info/top_level.txt
feastdays-1.1.0.dist-info/RECORD
